maq_rai_sdk_1-0.0.4.dist-info/licenses/LICENSE
rai_agent_sdk/__init__.py
rai_agent_sdk/_client.py
rai_agent_sdk/_configuration.py
rai_agent_sdk/_patch.py
rai_agent_sdk/py.typed
rai_agent_sdk/_utils/__init__.py
rai_agent_sdk/_utils/serialization.py
rai_agent_sdk/aio/__init__.py
rai_agent_sdk/aio/_client.py
rai_agent_sdk/aio/_configuration.py
rai_agent_sdk/aio/_patch.py
rai_agent_sdk/aio/operations/__init__.py
rai_agent_sdk/aio/operations/_operations.py
rai_agent_sdk/aio/operations/_patch.py
rai_agent_sdk/operations/__init__.py
rai_agent_sdk/operations/_operations.py
rai_agent_sdk/operations/_patch.py
maq_rai_sdk_1-0.0.4.dist-info/METADATA
maq_rai_sdk_1-0.0.4.dist-info/WHEEL
maq_rai_sdk_1-0.0.4.dist-info/top_level.txt
maq_rai_sdk_1-0.0.4.dist-info/RECORD
