Metadata-Version: 2.4
Name: maq-rai-sdk-1
Version: 0.0.4
Summary: RAI Package contains a Prompt Reviewer and Updater and test case generator for faster Copilot Development
Home-page: https://github.com/MAQ-Software-Solutions/maqraisdk
Author: MAQ Software
Author-email: MAQ Software <register@maqsoftware.com>
Maintainer-email: MAQ Software <register@maqsoftware.com>
License: MIT
Project-URL: Homepage, https://github.com/MAQ-Software-Solutions/maqraisdk
Project-URL: Repository, https://github.com/MAQ-Software-Solutions/maqraisdk
Project-URL: Documentation, https://github.com/MAQ-Software-Solutions/maqraisdk
Project-URL: Bug Reports, https://github.com/MAQ-Software-Solutions/maqraisdk/issues
Keywords: ai,copilot,prompt,testing,rai,agent
Classifier: Development Status :: 3 - Alpha
Classifier: Intended Audience :: Developers
Classifier: License :: OSI Approved :: MIT License
Classifier: Operating System :: OS Independent
Classifier: Programming Language :: Python :: 3
Classifier: Programming Language :: Python :: 3.10
Classifier: Programming Language :: Python :: 3.11
Classifier: Programming Language :: Python :: 3.12
Classifier: Programming Language :: Python :: 3.13
Classifier: Topic :: Software Development :: Libraries :: Python Modules
Requires-Python: >=3.10,<3.14
License-File: LICENSE
Requires-Dist: crewai[tools]==0.120.1
Requires-Dist: types-PyYAML==6.0.12.20250516
Requires-Dist: PyYAML==6.0.2
Requires-Dist: onnxruntime==1.22.0
Dynamic: author
Dynamic: home-page
Dynamic: license-file
Dynamic: requires-python
